sfetch/__init__.py
sfetch/colors.py
sfetch/helpers.py
sfetch/main.py
sfetch-1.0.3.dist-info/licenses/LICENSE
sfetch-1.0.3.dist-info/METADATA
sfetch-1.0.3.dist-info/WHEEL
sfetch-1.0.3.dist-info/entry_points.txt
sfetch-1.0.3.dist-info/top_level.txt
sfetch-1.0.3.dist-info/RECORD
