Metadata-Version: 2.4
Name: sfetch
Version: 1.0.3
Summary: Command-line tool for displaying spotify artist and album information. 
Author-email: Miha Šket <sket.miha@proton.me>
Project-URL: Homepage, https://github.com/mihasket/sfetch
Project-URL: Issues, https://github.com/mihasket/sfetch/issues
Classifier: Programming Language :: Python :: 3
Classifier: License :: OSI Approved :: MIT License
Classifier: Operating System :: OS Independent
Requires-Python: >=3.8
License-File: LICENSE
Requires-Dist: spotipy
Requires-Dist: climage
Requires-Dist: python-dotenv
Dynamic: license-file
